baodebug/__init__.py
baodebug/debugutils.py
baodebug-0.1.0.dist-info/METADATA
baodebug-0.1.0.dist-info/WHEEL
baodebug-0.1.0.dist-info/licenses/LICENSE
baodebug-0.1.0.dist-info/RECORD
